siunitpy/__init__.py
siunitpy/constant.py
siunitpy/dimension.py
siunitpy/dimension.pyi
siunitpy/dimensionconst.py
siunitpy/quantity.py
siunitpy/quntity.pyi
siunitpy/temperature.py
siunitpy/unit.py
siunitpy/unit.pyi
siunitpy/unit_analysis.py
siunitpy/unit_data.py
siunitpy/unitconst.py
siunitpy/SI/SIprefix.py
siunitpy/SI/SIquantity.py
siunitpy/SI/SIunit.py
siunitpy/SI/__init__.py
siunitpy/templatelib/__init__.py
siunitpy/templatelib/compound.py
siunitpy/templatelib/compound.pyi
siunitpy/templatelib/constclass.py
siunitpy/templatelib/continuedfraction.py
siunitpy/templatelib/continuedfraction.pyi
siunitpy/templatelib/utils.py
siunitpy/templatelib/value.py
siunitpy/templatelib/vector.py
siunitpy/templatelib/vector.pyi
siunitpy-0.0.2.dist-info/LICENSE
siunitpy-0.0.2.dist-info/METADATA
siunitpy-0.0.2.dist-info/WHEEL
siunitpy-0.0.2.dist-info/top_level.txt
siunitpy-0.0.2.dist-info/RECORD
