Metadata-Version: 2.1
Name: siunitpy
Version: 0.0.2
Summary: A package for SI units and uncertainty
Author-email: Dait <daitthu@qq.com>
Project-URL: Homepage, https://github.com/DaitTHU/siunitpy
Project-URL: Issues, https://github.com/DaitTHU/siunitpy/issues
Classifier: Programming Language :: Python :: 3
Classifier: License :: OSI Approved :: GNU General Public License v3 (GPLv3)
Requires-Python: >=3.9
License-File: LICENSE
